treact/__init__.py
treact/core.py
treact/renderers/__init__.py
treact/renderers/console.py
treact/renderers/html.py
treact/renderers/tree.py
treact-0.0.1.dist-info/METADATA
treact-0.0.1.dist-info/WHEEL
treact-0.0.1.dist-info/licenses/LICENSE.txt
treact-0.0.1.dist-info/RECORD
