Metadata-Version: 2.1
Name: treact
Version: 0.0.1
Project-URL: Documentation, https://github.com/pavi2410/treact#readme
Project-URL: Issues, https://github.com/pavi2410/treact/issues
Project-URL: Source, https://github.com/pavi2410/treact
Author-email: Pavitra Golchha <hello@pavi2410.me>
License-Expression: MIT
License-File: LICENSE.txt
Classifier: Development Status :: 4 - Beta
Classifier: Programming Language :: Python
Classifier: Programming Language :: Python :: 3.7
Classifier: Programming Language :: Python :: 3.8
Classifier: Programming Language :: Python :: 3.9
Classifier: Programming Language :: Python :: 3.10
Classifier: Programming Language :: Python :: 3.11
Classifier: Programming Language :: Python :: Implementation :: CPython
Classifier: Programming Language :: Python :: Implementation :: PyPy
Requires-Python: >=3.7
